py_nycmta/__init__.py
py_nycmta/exceptions.py
py_nycmta/train.py
py_nycmta/models/__init__.py
py_nycmta/models/arrivals.py
py_nycmta/utils/__init__.py
py_nycmta/utils/constants.py
py_nycmta/utils/gtfs.py
py_nycmta/utils/retry.py
py_nycmta/utils/subway_lines.py
py_nycmta/utils/subway_stations.py
py_nycmta-0.2.0.dist-info/METADATA
py_nycmta-0.2.0.dist-info/WHEEL
py_nycmta-0.2.0.dist-info/licenses/LICENSE
py_nycmta-0.2.0.dist-info/RECORD
