Metadata-Version: 2.4
Name: py-nycmta
Version: 0.2.0
Summary: Lightweight Python library for NYC MTA train arrival times
Project-URL: Homepage, https://github.com/dvd-rsnw/py-nycmta
Project-URL: Issues, https://github.com/dvd-rsnw/py-nycmta/issues
Project-URL: Repository, https://github.com/dvd-rsnw/py-nycmta
Author-email: David Rosenow <dvdrsnw@gmail.com>
License-File: LICENSE
Keywords: gtfs,metro,mta,new-york,nyc,public-transport,subway,train,transit
Classifier: Development Status :: 4 - Beta
Classifier: Intended Audience :: Developers
Classifier: License :: OSI Approved :: MIT License
Classifier: Operating System :: OS Independent
Classifier: Programming Language :: Python :: 3
Classifier: Programming Language :: Python :: 3.8
Classifier: Programming Language :: Python :: 3.9
Classifier: Programming Language :: Python :: 3.10
Classifier: Programming Language :: Python :: 3.11
Classifier: Programming Language :: Python :: 3.12
Classifier: Topic :: Internet :: WWW/HTTP :: Dynamic Content
Classifier: Topic :: Scientific/Engineering
Classifier: Topic :: Software Development :: Libraries :: Python Modules
Classifier: Typing :: Typed
Requires-Python: >=3.8
Requires-Dist: gtfs-realtime-bindings>=1.0.0
Requires-Dist: httpx>=0.24.0
Requires-Dist: protobuf>=4.20.0
Provides-Extra: dev
Requires-Dist: black>=22.0.0; extra == 'dev'
Requires-Dist: mypy>=1.0.0; extra == 'dev'
Requires-Dist: pytest-asyncio>=0.21.0; extra == 'dev'
Requires-Dist: pytest>=7.0.0; extra == 'dev'
Requires-Dist: ruff>=0.1.0; extra == 'dev'
